mercadopago/__init__.py
mercadopago/mercadopago.py
mercadopago_sdk_fork-1.1.3.dist-info/LICENSE
mercadopago_sdk_fork-1.1.3.dist-info/METADATA
mercadopago_sdk_fork-1.1.3.dist-info/WHEEL
mercadopago_sdk_fork-1.1.3.dist-info/top_level.txt
mercadopago_sdk_fork-1.1.3.dist-info/RECORD
