Metadata-Version: 2.1
Name: mercadopago-sdk-fork
Version: 1.1.3
Summary: Mercadopago SDK module for Payments integration
Home-page: https://github.com/mercadopago/sdk-python
Author: Horacio Casatti <horacio.casatti@mercadolibre.com>
Author-email: horacio.casatti@mercadolibre.com
License: UNKNOWN
Keywords: api mercadopago checkout payment ipn sdk integration
Platform: UNKNOWN
Classifier: Development Status :: 4 - Beta
Classifier: Intended Audience :: Developers
Classifier: Operating System :: OS Independent
Classifier: Programming Language :: Python
Classifier: Programming Language :: Python :: 2
Classifier: Programming Language :: Python :: 3.4
Classifier: Topic :: Software Development :: Libraries :: Python Modules
Classifier: License :: Freely Distributable
Requires-Dist: requests (>=2.4.3)
